collective.behavior.amp-1.0a2-py2.7-nspkg.pth
collective/behavior/amp/__init__.py
collective/behavior/amp/behaviors.py
collective/behavior/amp/behaviors.zcml
collective/behavior/amp/config.py
collective/behavior/amp/configure.zcml
collective/behavior/amp/interfaces.py
collective/behavior/amp/logger.py
collective/behavior/amp/profiles.zcml
collective/behavior/amp/setuphandlers.py
collective/behavior/amp/testing.py
collective/behavior/amp/utils.py
collective/behavior/amp/validators.py
collective/behavior/amp/Extensions/Install.py
collective/behavior/amp/Extensions/__init__.py
collective/behavior/amp/browser/__init__.py
collective/behavior/amp/browser/configure.zcml
collective/behavior/amp/browser/controlpanel.py
collective/behavior/amp/browser/helper.py
collective/behavior/amp/browser/view.pt
collective/behavior/amp/browser/viewlet.pt
collective/behavior/amp/browser/static/amp-icon.png
collective/behavior/amp/browser/static/bars.svg
collective/behavior/amp/browser/static/close.svg
collective/behavior/amp/locales/collective.behavior.amp.pot
collective/behavior/amp/locales/manual.pot
collective/behavior/amp/locales/plone.pot
collective/behavior/amp/locales/es/LC_MESSAGES/collective.behavior.amp.po
collective/behavior/amp/locales/es/LC_MESSAGES/plone.po
collective/behavior/amp/locales/pt_BR/LC_MESSAGES/collective.behavior.amp.po
collective/behavior/amp/locales/pt_BR/LC_MESSAGES/plone.po
collective/behavior/amp/profiles/default/browserlayer.xml
collective/behavior/amp/profiles/default/controlpanel.xml
collective/behavior/amp/profiles/default/metadata.xml
collective/behavior/amp/profiles/default/registry.xml
collective/behavior/amp/profiles/default/rolemap.xml
collective/behavior/amp/profiles/uninstall/controlpanel.xml
collective/behavior/amp/profiles/uninstall/registry.xml
collective/behavior/amp/tests/__init__.py
collective/behavior/amp/tests/logo-plone-bigger.png
collective/behavior/amp/tests/logo-plone-ok.png
collective.behavior.amp-1.0a2.dist-info/DESCRIPTION.rst
collective.behavior.amp-1.0a2.dist-info/METADATA
collective.behavior.amp-1.0a2.dist-info/RECORD
collective.behavior.amp-1.0a2.dist-info/WHEEL
collective.behavior.amp-1.0a2.dist-info/entry_points.txt
collective.behavior.amp-1.0a2.dist-info/metadata.json
collective.behavior.amp-1.0a2.dist-info/namespace_packages.txt
collective.behavior.amp-1.0a2.dist-info/top_level.txt
