Metadata-Version: 2.0
Name: collective.behavior.amp
Version: 1.0a2
Summary: Support for Accelerated Mobile Pages (AMP) on Dexterity-based content types.
Home-page: https://github.com/collective/collective.behavior.amp
Author: Simples Consultoria
Author-email: produtos@simplesconsultoria.com.br
License: UNKNOWN
Keywords: plone amp mobile dexterity behavior
Platform: UNKNOWN
Classifier: Development Status :: 3 - Alpha
Classifier: Environment :: Web Environment
Classifier: Framework :: Plone
Classifier: Framework :: Plone :: 4.3
Classifier: Framework :: Plone :: 5.0
Classifier: Framework :: Plone :: 5.1
Classifier: Intended Audience :: System Administrators
Classifier: License :: OSI Approved :: GNU General Public License v2 (GPLv2)
Classifier: Operating System :: OS Independent
Classifier: Programming Language :: Python
Classifier: Programming Language :: Python :: 2.7
Classifier: Topic :: Office/Business :: News/Diary
Classifier: Topic :: Software Development :: Libraries :: Python Modules
Requires-Dist: Products.CMFCore
Requires-Dist: Products.CMFPlone (>=4.3)
Requires-Dist: Products.GenericSetup
Requires-Dist: lxml
Requires-Dist: plone.api
Requires-Dist: plone.app.layout
Requires-Dist: plone.app.registry
Requires-Dist: plone.app.textfield
Requires-Dist: plone.autoform
Requires-Dist: plone.behavior
Requires-Dist: plone.dexterity
Requires-Dist: plone.formwidget.namedfile
Requires-Dist: plone.memoize
Requires-Dist: plone.namedfile
Requires-Dist: plone.supermodel
Requires-Dist: setuptools
Requires-Dist: zope.i18nmessageid
Requires-Dist: zope.interface
Requires-Dist: zope.schema
Provides-Extra: test
Requires-Dist: AccessControl; extra == 'test'
Requires-Dist: plone.app.contenttypes; extra == 'test'
Requires-Dist: plone.app.robotframework; extra == 'test'
Requires-Dist: plone.app.testing[robot]; extra == 'test'
Requires-Dist: plone.browserlayer; extra == 'test'
Requires-Dist: plone.registry; extra == 'test'
Requires-Dist: plone.testing; extra == 'test'
Requires-Dist: robotsuite; extra == 'test'
Requires-Dist: z3c.relationfield; extra == 'test'
Requires-Dist: zope.component; extra == 'test'
Requires-Dist: zope.intid; extra == 'test'
